autossh/__init__.py
autossh/autossh_py.py
autossh/client.py
autossh-0.0.1.3.dist-info/LICENSE
autossh-0.0.1.3.dist-info/METADATA
autossh-0.0.1.3.dist-info/WHEEL
autossh-0.0.1.3.dist-info/entry_points.txt
autossh-0.0.1.3.dist-info/top_level.txt
autossh-0.0.1.3.dist-info/RECORD
