Metadata-Version: 2.1
Name: autossh
Version: 0.0.1.3
Summary: A simple auto reconnect ssh tunnel client
Author: Gavin Bao
Author-email: xingce.bao@gmail.com
License: MIT
License-File: LICENSE
Requires-Dist: sshtunnel
